victoriabank_mia_sdk/__init__.py
victoriabank_mia_sdk/victoriabank_mia_api.py
victoriabank_mia_sdk/victoriabank_mia_auth.py
victoriabank_mia_sdk/victoriabank_mia_sdk.py
victoriabank_mia_sdk-1.1.4.dist-info/licenses/LICENSE
victoriabank_mia_sdk-1.1.4.dist-info/METADATA
victoriabank_mia_sdk-1.1.4.dist-info/WHEEL
victoriabank_mia_sdk-1.1.4.dist-info/top_level.txt
victoriabank_mia_sdk-1.1.4.dist-info/RECORD
